{
  "name": "aiida-feff dev",
  "dockerComposeFile": "docker-compose.yml",
  "service": "app",
  "workspaceFolder": "/workspace",

  "features": {
    "ghcr.io/devcontainers/features/common-utils:2": {
      "installZsh": true,
      "configureZshAsDefaultShell": true
    }
  },

  "customizations": {
    "vscode": {
      "extensions": [
        "ms-python.python",
        "ms-python.vscode-pylance",
        "github.copilot",
        "tamasfe.even-better-toml"
      ],
      "settings": {
        "python.defaultInterpreterPath": "/workspace/.venv/bin/python",
        "python.testing.pytestEnabled": true,
        "python.testing.pytestArgs": ["tests"]
      }
    }
  },

  "postCreateCommand": "bash .devcontainer/post-create.sh",

  "remoteUser": "vscode",
  "updateRemoteUserUID": false,

  "forwardPorts": [8888],
  "portsAttributes": {
    "8888": { "label": "Jupyter" }
  }
}
